neosctl/__init__.py
neosctl/cli.py
neosctl/constant.py
neosctl/env.py
neosctl/http.py
neosctl/info.py
neosctl/schema.py
neosctl/util.py
neosctl/services/__init__.py
neosctl/services/gateway/__init__.py
neosctl/services/gateway/data_product.py
neosctl/services/gateway/data_source.py
neosctl/services/gateway/data_system.py
neosctl/services/gateway/data_unit.py
neosctl/services/gateway/entity.py
neosctl/services/gateway/journal_note.py
neosctl/services/gateway/link.py
neosctl/services/gateway/output.py
neosctl/services/gateway/schema.py
neosctl/services/gateway/secret.py
neosctl/services/gateway/spark.py
neosctl/services/gateway/tag.py
neosctl/services/iam/__init__.py
neosctl/services/iam/iam.py
neosctl/services/iam/schema.py
neosctl/services/registry/__init__.py
neosctl/services/registry/registry.py
neosctl/services/registry/schema.py
neosctl/services/storage/__init__.py
neosctl/services/storage/storage.py
neosctl-0.13.2.dist-info/METADATA
neosctl-0.13.2.dist-info/WHEEL
neosctl-0.13.2.dist-info/entry_points.txt
neosctl-0.13.2.dist-info/RECORD
