Metadata-Version: 2.3
Name: neosctl
Version: 0.13.2
Summary: NEOS Core CLI
Requires-Python: >=3.9
Requires-Dist: auth-aws4>=0.1.2
Requires-Dist: httpx>=0.27
Requires-Dist: minio>=7.1.14
Requires-Dist: multidict>=6.0.5
Requires-Dist: orjson>=3.10.1
Requires-Dist: pydantic>=2.0.0
Requires-Dist: rich>=13.7.1
Requires-Dist: rtoml>=0.10.0
Requires-Dist: ryaml>=0.4.0
Requires-Dist: tabulate>=0.9.0
Requires-Dist: typer>=0.12
Requires-Dist: typing-extensions>=4.7.0; python_version <= '3.10'
Provides-Extra: dev
Requires-Dist: changelog-gen<0.14,>=0.13.2; extra == 'dev'
Requires-Dist: freezegun>=1.2.1; extra == 'dev'
Requires-Dist: pdoc>=14.1.0; extra == 'dev'
Requires-Dist: pre-commit>=3.7.1; extra == 'dev'
Requires-Dist: pyright>=1.1.293; extra == 'dev'
Requires-Dist: pytest-cov>=3.0.0; extra == 'dev'
Requires-Dist: pytest-httpx>=0.30; extra == 'dev'
Requires-Dist: pytest-random-order>=1.0.4; extra == 'dev'
Requires-Dist: pytest<7.2,>=7.1.2; extra == 'dev'
Requires-Dist: ruff>=0.6.4; extra == 'dev'
